gfparser/__init__.py
gfparser/_nbdev.py
gfparser/config.py
gfparser/wikiparser.py
gfparser/word.py
gfparser/wordtype.py
gfparser-0.0.1.dist-info/LICENSE
gfparser-0.0.1.dist-info/METADATA
gfparser-0.0.1.dist-info/WHEEL
gfparser-0.0.1.dist-info/entry_points.txt
gfparser-0.0.1.dist-info/top_level.txt
gfparser-0.0.1.dist-info/RECORD
