Metadata-Version: 2.1
Name: gfparser
Version: 0.0.1
Summary: Pulls useful information from the web helping you make flashcards for learning the German language
Home-page: https://github.com/nmarincic/gfparser/tree/master/
Author: Nikola Marincic
Author-email: nikola.marincic@gmail.com
License: Apache Software License 2.0
Keywords: german learning python flashcards anki wiktionary deutsch forvo
Platform: UNKNOWN
Classifier: Development Status :: 3 - Alpha
Classifier: Intended Audience :: Developers
Classifier: License :: OSI Approved :: Apache Software License
Classifier: Natural Language :: English
Classifier: Programming Language :: Python :: 3.6
Classifier: Programming Language :: Python :: 3.7
Classifier: Programming Language :: Python :: 3.8
Requires-Python: >=3.6
Requires-Dist: fastcore
Requires-Dist: requests
Requires-Dist: pyprind
Requires-Dist: prettytable
